LICENSE
MANIFEST.in
README.rst
setup.cfg
setup.py
adoptions/__init__.py
adoptions/admin.py
adoptions/apps.py
adoptions/models.py
adoptions/tests.py
adoptions/urls.py
adoptions/views.py
adoptions/migrations/0001_initial.py
adoptions/migrations/__init__.py
adoptions/static/main.js
adoptions/static/style.css
adoptions/templates/adoptions/base.html
adoptions/templates/adoptions/home.html
adoptions/templates/adoptions/pet_detail.html
django_wisdom_pets.egg-info/PKG-INFO
django_wisdom_pets.egg-info/SOURCES.txt
django_wisdom_pets.egg-info/dependency_links.txt
django_wisdom_pets.egg-info/top_level.txt